ampt2/__init__.py
ampt2/ampt2.py
ampt2-0.0.2.dist-info/METADATA
ampt2-0.0.2.dist-info/WHEEL
ampt2-0.0.2.dist-info/entry_points.txt
ampt2-0.0.2.dist-info/top_level.txt
ampt2-0.0.2.dist-info/RECORD
