Metadata-Version: 2.1
Name: ampt2
Version: 0.0.2
Summary: Andy Meng's Python Test
Home-page: https://juejin.cn/user/2875978147966855
Author: Andy Meng
Author-email: andy_m129@163.com
License: UNKNOWN
Project-URL: Bug Tracker, https://github.com/pypa/sampleproject/issues
Platform: UNKNOWN
Classifier: Programming Language :: Python :: 3
Classifier: License :: OSI Approved :: MIT License
Classifier: Operating System :: OS Independent
Requires-Python: >=3.6
